metabci/__init__.py
metabci/brainda/__init__.py
metabci/brainda/algorithms/__init__.py
metabci/brainda/algorithms/decomposition/SKLDA.py
metabci/brainda/algorithms/decomposition/STDA.py
metabci/brainda/algorithms/decomposition/__init__.py
metabci/brainda/algorithms/decomposition/base.py
metabci/brainda/algorithms/decomposition/cca.py
metabci/brainda/algorithms/decomposition/csp.py
metabci/brainda/algorithms/decomposition/dsp.py
metabci/brainda/algorithms/decomposition/sceTRCA.py
metabci/brainda/algorithms/decomposition/sscor.py
metabci/brainda/algorithms/decomposition/tdca.py
metabci/brainda/algorithms/deep_learning/__init__.py
metabci/brainda/algorithms/deep_learning/base.py
metabci/brainda/algorithms/deep_learning/convca.py
metabci/brainda/algorithms/deep_learning/deepnet.py
metabci/brainda/algorithms/deep_learning/eegnet.py
metabci/brainda/algorithms/deep_learning/guney_net.py
metabci/brainda/algorithms/deep_learning/pretraining.py
metabci/brainda/algorithms/deep_learning/shallownet.py
metabci/brainda/algorithms/dynamic_stopping/__init__.py
metabci/brainda/algorithms/dynamic_stopping/bayes.py
metabci/brainda/algorithms/dynamic_stopping/ce.py
metabci/brainda/algorithms/dynamic_stopping/lda.py
metabci/brainda/algorithms/feature_analysis/__init__.py
metabci/brainda/algorithms/feature_analysis/freq_analysis.py
metabci/brainda/algorithms/feature_analysis/time_analysis.py
metabci/brainda/algorithms/feature_analysis/time_freq_analysis.py
metabci/brainda/algorithms/manifold/__init__.py
metabci/brainda/algorithms/manifold/riemann.py
metabci/brainda/algorithms/manifold/rpa.py
metabci/brainda/algorithms/transfer_learning/__init__.py
metabci/brainda/algorithms/transfer_learning/base.py
metabci/brainda/algorithms/transfer_learning/lst.py
metabci/brainda/algorithms/transfer_learning/mekt.py
metabci/brainda/algorithms/transfer_learning/same.py
metabci/brainda/algorithms/utils/__init__.py
metabci/brainda/algorithms/utils/covariance.py
metabci-0.2.0.dist-info/licenses/LICENSE
metabci-0.2.0.dist-info/METADATA
metabci-0.2.0.dist-info/WHEEL
metabci-0.2.0.dist-info/top_level.txt
metabci-0.2.0.dist-info/RECORD
