Metadata-Version: 2.4
Name: metabci
Version: 0.2.0
Summary: A Library of Datasets, Algorithms, and Experiments workflow for Brain-Computer Interface
Author-email: TBC-TJU <TBC_TJU_2022@163.com>
License: GPL-2.0
Project-URL: Homepage, https://github.com/TBC-TJU/MetaBCI
Project-URL: Documentation, https://metabci.readthedocs.io
Project-URL: Repository, https://github.com/TBC-TJU/MetaBCI
Keywords: brain-computer interface,BCI,EEG,neuroscience,machine learning
Classifier: Programming Language :: Python :: 3
Classifier: Programming Language :: Python :: 3.9
Classifier: Programming Language :: Python :: 3.10
Classifier: Programming Language :: Python :: 3.11
Classifier: Programming Language :: Python :: 3.12
Classifier: Programming Language :: Python :: 3.13
Classifier: License :: OSI Approved :: GNU General Public License v2 (GPLv2)
Classifier: Operating System :: OS Independent
Classifier: Intended Audience :: Science/Research
Classifier: Topic :: Scientific/Engineering :: Human Machine Interfaces
Requires-Python: >=3.9
License-File: LICENSE
Requires-Dist: numpy
Requires-Dist: scipy
Requires-Dist: tqdm>=4.32.0
Requires-Dist: requests
Requires-Dist: requests[socks]
Requires-Dist: joblib
Provides-Extra: brainda
Requires-Dist: mne>=0.21.1; extra == "brainda"
Requires-Dist: mne-bids; extra == "brainda"
Requires-Dist: pandas; extra == "brainda"
Requires-Dist: scikit-learn; extra == "brainda"
Requires-Dist: h5py; extra == "brainda"
Requires-Dist: mat73; extra == "brainda"
Requires-Dist: py7zr; extra == "brainda"
Requires-Dist: pooch; extra == "brainda"
Requires-Dist: torch>=1.7.1; extra == "brainda"
Requires-Dist: skorch; extra == "brainda"
Requires-Dist: autograd; extra == "brainda"
Requires-Dist: pymanopt>=2.0; extra == "brainda"
Provides-Extra: brainflow
Requires-Dist: pylsl; extra == "brainflow"
Provides-Extra: brainstim
Requires-Dist: pylsl; extra == "brainstim"
Requires-Dist: psychopy>=2022.1.4; extra == "brainstim"
Provides-Extra: all
Requires-Dist: metabci[brainda,brainflow,brainstim]; extra == "all"
Provides-Extra: dev
Requires-Dist: pytest; extra == "dev"
Requires-Dist: coverage; extra == "dev"
Requires-Dist: flake8; extra == "dev"
Requires-Dist: mypy; extra == "dev"
Provides-Extra: docs
Requires-Dist: Sphinx; extra == "docs"
Requires-Dist: sphinx-rtd-theme; extra == "docs"
Requires-Dist: sphinxcontrib-napoleon; extra == "docs"
Requires-Dist: sphinxcontrib-apidoc; extra == "docs"
Requires-Dist: m2r2; extra == "docs"
Dynamic: license-file
